rapidgzip.cpython-39-i386-linux-gnu.so
rapidgzip.libs/libgcc_s-e1925712.so.1
rapidgzip.libs/libstdc++-b2d5af4b.so.6.0.33
rapidgzip-0.15.2.dist-info/LICENSE-APACHE
rapidgzip-0.15.2.dist-info/LICENSE-MIT
rapidgzip-0.15.2.dist-info/METADATA
rapidgzip-0.15.2.dist-info/WHEEL
rapidgzip-0.15.2.dist-info/entry_points.txt
rapidgzip-0.15.2.dist-info/top_level.txt
rapidgzip-0.15.2.dist-info/RECORD
